{
  "BOX": {
    "price": "3.61pln",
    "winChance": 27.789,
    "looseChance": 72.211,
    "profitChances": {
      "<1.25": "8.9%",
      "1.25 - 1.49": "0.66%",
      "1.5 - 1.74": "3.65%",
      "1.75 - 1.99": "7.14%",
      "2 - 2.24": "2.57%",
      "2.25 - 2.4": "0%",
      "2.5 - 2.75": "0.57%",
      "2.75 - 2.99": "2.68%",
      ">3": "1.63%"
    }
  },
  "FOG": {
    "price": "23.68pln",
    "winChance": 32.946,
    "looseChance": 67.054,
    "profitChances": {
      "<1.25": "14.77%",
      "1.25 - 1.49": "0.53%",
      "1.5 - 1.74": "3.11%",
      "1.75 - 1.99": "5.81%",
      "2 - 2.24": "0%",
      "2.25 - 2.4": "3.23%",
      "2.5 - 2.75": "1.33%",
      "2.75 - 2.99": "0%",
      ">3": "4.17%"
    }
  },
  "STARLIGHT": {
    "price": "99.22pln",
    "winChance": 34.798,
    "looseChance": 65.202,
    "profitChances": {
      "<1.25": "14.01%",
      "1.25 - 1.49": "2.16%",
      "1.5 - 1.74": "6.76%",
      "1.75 - 1.99": "2.79%",
      "2 - 2.24": "4.34%",
      "2.25 - 2.4": "2.28%",
      "2.5 - 2.75": "0.69%",
      "2.75 - 2.99": "0.59%",
      ">3": "1.18%"
    }
  },
  "PEEK": {
    "price": "39.46pln",
    "winChance": 36.194,
    "looseChance": 63.806,
    "profitChances": {
      "<1.25": "16.49%",
      "1.25 - 1.49": "2.48%",
      "1.5 - 1.74": "6.06%",
      "1.75 - 1.99": "6.58%",
      "2 - 2.24": "1.81%",
      "2.25 - 2.4": "0.18%",
      "2.5 - 2.75": "2.04%",
      "2.75 - 2.99": "0.16%",
      ">3": "0.4%"
    }
  },
  "REVOLUTION": {
    "price": "7.22pln",
    "winChance": 37.861,
    "looseChance": 62.139,
    "profitChances": {
      "<1.25": "13.22%",
      "1.25 - 1.49": "10.59%",
      "1.5 - 1.74": "1.24%",
      "1.75 - 1.99": "0%",
      "2 - 2.24": "0.89%",
      "2.25 - 2.4": "5.13%",
      "2.5 - 2.75": "0%",
      "2.75 - 2.99": "5.13%",
      ">3": "1.66%"
    }
  },
  "VOLT": {
    "price": "11.27pln",
    "winChance": 12.736,
    "looseChance": 87.264,
    "profitChances": {
      "<1.25": "0%",
      "1.25 - 1.49": "1.18%",
      "1.5 - 1.74": "2.44%",
      "1.75 - 1.99": "1.12%",
      "2 - 2.24": "2.18%",
      "2.25 - 2.4": "0%",
      "2.5 - 2.75": "1.37%",
      "2.75 - 2.99": "0%",
      ">3": "4.44%"
    }
  },
  "SABRE": {
    "price": "11.27pln",
    "winChance": 22.57,
    "looseChance": 77.43,
    "profitChances": {
      "<1.25": "5.2%",
      "1.25 - 1.49": "0%",
      "1.5 - 1.74": "2.5%",
      "1.75 - 1.99": "6.5%",
      "2 - 2.24": "0%",
      "2.25 - 2.4": "1.2%",
      "2.5 - 2.75": "0.5%",
      "2.75 - 2.99": "1.2%",
      ">3": "5.47%"
    }
  },
  "INFINITY": {
    "price": "11.27pln",
    "winChance": 16.742,
    "looseChance": 83.258,
    "profitChances": {
      "<1.25": "0.57%",
      "1.25 - 1.49": "3.6%",
      "1.5 - 1.74": "1.88%",
      "1.75 - 1.99": "5.16%",
      "2 - 2.24": "1.54%",
      "2.25 - 2.4": "0.28%",
      "2.5 - 2.75": "0.99%",
      "2.75 - 2.99": "0.78%",
      ">3": "1.95%"
    }
  },
  "STORM": {
    "price": "11.27pln",
    "winChance": 37.5,
    "looseChance": 62.5,
    "profitChances": {
      "<1.25": "5.2%",
      "1.25 - 1.49": "25%",
      "1.5 - 1.74": "0%",
      "1.75 - 1.99": "0%",
      "2 - 2.24": "0%",
      "2.25 - 2.4": "2.9%",
      "2.5 - 2.75": "0%",
      "2.75 - 2.99": "0%",
      ">3": "4.4%"
    }
  },
  "DUST": {
    "price": "11.27pln",
    "winChance": 24.815,
    "looseChance": 75.185,
    "profitChances": {
      "<1.25": "2.94%",
      "1.25 - 1.49": "10.46%",
      "1.5 - 1.74": "3.49%",
      "1.75 - 1.99": "3.88%",
      "2 - 2.24": "0%",
      "2.25 - 2.4": "1.61%",
      "2.5 - 2.75": "0.92%",
      "2.75 - 2.99": "0%",
      ">3": "1.51%"
    }
  },
  "KACPER RIETZ": {
    "price": "19.75pln",
    "winChance": 29.565,
    "looseChance": 70.435,
    "profitChances": {
      "<1.25": "0.52%",
      "1.25 - 1.49": "10.95%",
      "1.5 - 1.74": "4.25%",
      "1.75 - 1.99": "3.84%",
      "2 - 2.24": "2.79%",
      "2.25 - 2.4": "3.15%",
      "2.5 - 2.75": "0.54%",
      "2.75 - 2.99": "2.11%",
      ">3": "1.42%"
    }
  },
  "MATEO": {
    "price": "19.75pln",
    "winChance": 17.517,
    "looseChance": 82.483,
    "profitChances": {
      "<1.25": "0%",
      "1.25 - 1.49": "0%",
      "1.5 - 1.74": "0.2%",
      "1.75 - 1.99": "0%",
      "2 - 2.24": "0%",
      "2.25 - 2.4": "0%",
      "2.5 - 2.75": "0%",
      "2.75 - 2.99": "4.38%",
      ">3": "12.93%"
    }
  },
  "ISAMU": {
    "price": "49.43pln",
    "winChance": 31.879,
    "looseChance": 68.121,
    "profitChances": {
      "<1.25": "4.8%",
      "1.25 - 1.49": "13.84%",
      "1.5 - 1.74": "8.79%",
      "1.75 - 1.99": "1.37%",
      "2 - 2.24": "0.42%",
      "2.25 - 2.4": "0.51%",
      "2.5 - 2.75": "0.45%",
      "2.75 - 2.99": "0.3%",
      ">3": "1.42%"
    }
  },
  "MEDUSA": {
    "price": "33.6pln",
    "winChance": 33.114,
    "looseChance": 66.886,
    "profitChances": {
      "<1.25": "4.68%",
      "1.25 - 1.49": "15.94%",
      "1.5 - 1.74": "7.84%",
      "1.75 - 1.99": "0.4%",
      "2 - 2.24": "1.94%",
      "2.25 - 2.4": "1.74%",
      "2.5 - 2.75": "0%",
      "2.75 - 2.99": "0%",
      ">3": "0.58%"
    }
  },
  "INNOCENT": {
    "price": "27.69pln",
    "winChance": 33.924,
    "looseChance": 66.076,
    "profitChances": {
      "<1.25": "7.57%",
      "1.25 - 1.49": "11.38%",
      "1.5 - 1.74": "3.92%",
      "1.75 - 1.99": "4.3%",
      "2 - 2.24": "4.4%",
      "2.25 - 2.4": "0.21%",
      "2.5 - 2.75": "0%",
      "2.75 - 2.99": "0.72%",
      ">3": "1.43%"
    }
  },
  "DMG": {
    "price": "100.03pln",
    "winChance": 27.326,
    "looseChance": 72.674,
    "profitChances": {
      "<1.25": "2.48%",
      "1.25 - 1.49": "0.2%",
      "1.5 - 1.74": "22.41%",
      "1.75 - 1.99": "0%",
      "2 - 2.24": "0%",
      "2.25 - 2.4": "0%",
      "2.5 - 2.75": "0.61%",
      "2.75 - 2.99": "0%",
      ">3": "1.63%"
    }
  },
  "GILATHISS": {
    "price": "49.43pln",
    "winChance": 36.545,
    "looseChance": 63.455,
    "profitChances": {
      "<1.25": "11.67%",
      "1.25 - 1.49": "9.69%",
      "1.5 - 1.74": "7.04%",
      "1.75 - 1.99": "0.68%",
      "2 - 2.24": "4.65%",
      "2.25 - 2.4": "0.14%",
      "2.5 - 2.75": "1.57%",
      "2.75 - 2.99": "0%",
      ">3": "1.11%"
    }
  },
  "NEXE": {
    "price": "33.37pln",
    "winChance": 25.697,
    "looseChance": 74.303,
    "profitChances": {
      "<1.25": "0.28%",
      "1.25 - 1.49": "2.54%",
      "1.5 - 1.74": "3.95%",
      "1.75 - 1.99": "1.61%",
      "2 - 2.24": "7.76%",
      "2.25 - 2.4": "0%",
      "2.5 - 2.75": "0%",
      "2.75 - 2.99": "0%",
      ">3": "9.56%"
    }
  },
  "JUANFLATROO": {
    "price": "39.55pln",
    "winChance": 37.118,
    "looseChance": 62.882,
    "profitChances": {
      "<1.25": "15.62%",
      "1.25 - 1.49": "8.12%",
      "1.5 - 1.74": "7.74%",
      "1.75 - 1.99": "0.52%",
      "2 - 2.24": "2.21%",
      "2.25 - 2.4": "1.98%",
      "2.5 - 2.75": "0%",
      "2.75 - 2.99": "0.6%",
      ">3": "0.33%"
    }
  },
  "ZONY": {
    "price": "47.45pln",
    "winChance": 10,
    "looseChance": 90,
    "profitChances": {
      "<1.25": "0%",
      "1.25 - 1.49": "0%",
      "1.5 - 1.74": "0%",
      "1.75 - 1.99": "0%",
      "2 - 2.24": "0%",
      "2.25 - 2.4": "0%",
      "2.5 - 2.75": "0%",
      "2.75 - 2.99": "0%",
      ">3": "10%"
    }
  },
  "SPARK": {
    "price": "6.9pln",
    "winChance": 1,
    "looseChance": 99,
    "profitChances": {
      "<1.25": "0%",
      "1.25 - 1.49": "0%",
      "1.5 - 1.74": "0%",
      "1.75 - 1.99": "0%",
      "2 - 2.24": "0%",
      "2.25 - 2.4": "0%",
      "2.5 - 2.75": "0%",
      "2.75 - 2.99": "0%",
      ">3": "1%"
    }
  },
  "DAGGERS": {
    "price": "2.39pln",
    "winChance": 1,
    "looseChance": 99,
    "profitChances": {
      "<1.25": "0%",
      "1.25 - 1.49": "0%",
      "1.5 - 1.74": "0%",
      "1.75 - 1.99": "0%",
      "2 - 2.24": "0%",
      "2.25 - 2.4": "0%",
      "2.5 - 2.75": "0%",
      "2.75 - 2.99": "0%",
      ">3": "1%"
    }
  },
  "PERFECT": {
    "price": "15.83pln",
    "winChance": 20.748,
    "looseChance": 79.252,
    "profitChances": {
      "<1.25": "0.47%",
      "1.25 - 1.49": "8.01%",
      "1.5 - 1.74": "3.62%",
      "1.75 - 1.99": "1.43%",
      "2 - 2.24": "0.64%",
      "2.25 - 2.4": "0%",
      "2.5 - 2.75": "0.86%",
      "2.75 - 2.99": "0%",
      ">3": "5.72%"
    }
  },
  "ENERGY": {
    "price": "2.39pln",
    "winChance": 3.06,
    "looseChance": 96.94,
    "profitChances": {
      "<1.25": "0%",
      "1.25 - 1.49": "0%",
      "1.5 - 1.74": "0%",
      "1.75 - 1.99": "0%",
      "2 - 2.24": "0%",
      "2.25 - 2.4": "0%",
      "2.5 - 2.75": "0%",
      "2.75 - 2.99": "0%",
      ">3": "3.06%"
    }
  },
  "SHARP": {
    "price": "39.55pln",
    "winChance": 22.194,
    "looseChance": 77.806,
    "profitChances": {
      "<1.25": "0%",
      "1.25 - 1.49": "0%",
      "1.5 - 1.74": "5.53%",
      "1.75 - 1.99": "10.74%",
      "2 - 2.24": "0%",
      "2.25 - 2.4": "0%",
      "2.5 - 2.75": "2.36%",
      "2.75 - 2.99": "0%",
      ">3": "3.56%"
    }
  },
  "SWAP": {
    "price": "15.83pln",
    "winChance": 2.75,
    "looseChance": 97.25,
    "profitChances": {
      "<1.25": "0%",
      "1.25 - 1.49": "0%",
      "1.5 - 1.74": "0%",
      "1.75 - 1.99": "0%",
      "2 - 2.24": "0%",
      "2.25 - 2.4": "0%",
      "2.5 - 2.75": "0%",
      "2.75 - 2.99": "0%",
      ">3": "2.75%"
    }
  },
  "SIGNAL": {
    "price": "14.84pln",
    "winChance": 9.5,
    "looseChance": 90.5,
    "profitChances": {
      "<1.25": "0%",
      "1.25 - 1.49": "0%",
      "1.5 - 1.74": "0%",
      "1.75 - 1.99": "0%",
      "2 - 2.24": "0%",
      "2.25 - 2.4": "0%",
      "2.5 - 2.75": "0%",
      "2.75 - 2.99": "0%",
      ">3": "9.5%"
    }
  },
  "SMART": {
    "price": "17.81pln",
    "winChance": 11.778,
    "looseChance": 88.222,
    "profitChances": {
      "<1.25": "4.33%",
      "1.25 - 1.49": "0%",
      "1.5 - 1.74": "0.69%",
      "1.75 - 1.99": "1.53%",
      "2 - 2.24": "0%",
      "2.25 - 2.4": "1.09%",
      "2.5 - 2.75": "0.51%",
      "2.75 - 2.99": "0%",
      ">3": "3.63%"
    }
  },
  "CAPITAL": {
    "price": "15.83pln",
    "winChance": 1.386,
    "looseChance": 98.614,
    "profitChances": {
      "<1.25": "0%",
      "1.25 - 1.49": "0%",
      "1.5 - 1.74": "0%",
      "1.75 - 1.99": "0%",
      "2 - 2.24": "0%",
      "2.25 - 2.4": "0%",
      "2.5 - 2.75": "0%",
      "2.75 - 2.99": "0%",
      ">3": "1.39%"
    }
  },
  "TECH": {
    "price": "2.39pln",
    "winChance": 1,
    "looseChance": 99,
    "profitChances": {
      "<1.25": "0%",
      "1.25 - 1.49": "0%",
      "1.5 - 1.74": "0%",
      "1.75 - 1.99": "0%",
      "2 - 2.24": "0%",
      "2.25 - 2.4": "0%",
      "2.5 - 2.75": "0%",
      "2.75 - 2.99": "0%",
      ">3": "1%"
    }
  },
  "1% PROFIT": {
    "price": "3.38pln",
    "winChance": 1,
    "looseChance": 99,
    "profitChances": {
      "<1.25": "0%",
      "1.25 - 1.49": "0%",
      "1.5 - 1.74": "0%",
      "1.75 - 1.99": "0%",
      "2 - 2.24": "0%",
      "2.25 - 2.4": "0%",
      "2.5 - 2.75": "0%",
      "2.75 - 2.99": "0%",
      ">3": "1%"
    }
  },
  "LORD": {
    "price": "19.75pln",
    "winChance": 13.473,
    "looseChance": 86.527,
    "profitChances": {
      "<1.25": "4.76%",
      "1.25 - 1.49": "5.92%",
      "1.5 - 1.74": "1%",
      "1.75 - 1.99": "0.43%",
      "2 - 2.24": "0.38%",
      "2.25 - 2.4": "0.35%",
      "2.5 - 2.75": "0%",
      "2.75 - 2.99": "0%",
      ">3": "0.63%"
    }
  },
  "TOKEN": {
    "price": "11.86pln",
    "winChance": 21.925,
    "looseChance": 78.075,
    "profitChances": {
      "<1.25": "0%",
      "1.25 - 1.49": "0%",
      "1.5 - 1.74": "0%",
      "1.75 - 1.99": "19.9%",
      "2 - 2.24": "0%",
      "2.25 - 2.4": "0%",
      "2.5 - 2.75": "0%",
      "2.75 - 2.99": "0%",
      ">3": "2.02%"
    }
  },
  "ROCKET": {
    "price": "19.75pln",
    "winChance": 5,
    "looseChance": 95,
    "profitChances": {
      "<1.25": "0%",
      "1.25 - 1.49": "0%",
      "1.5 - 1.74": "0%",
      "1.75 - 1.99": "0%",
      "2 - 2.24": "0%",
      "2.25 - 2.4": "0%",
      "2.5 - 2.75": "0%",
      "2.75 - 2.99": "0%",
      ">3": "5%"
    }
  },
  "1% KNIFE": {
    "price": "3.97pln",
    "winChance": 1,
    "looseChance": 99,
    "profitChances": {
      "<1.25": "0%",
      "1.25 - 1.49": "0%",
      "1.5 - 1.74": "0%",
      "1.75 - 1.99": "0%",
      "2 - 2.24": "0%",
      "2.25 - 2.4": "0%",
      "2.5 - 2.75": "0%",
      "2.75 - 2.99": "0%",
      ">3": "1%"
    }
  },
  "SPACE": {
    "price": "27.69pln",
    "winChance": 32.394,
    "looseChance": 67.606,
    "profitChances": {
      "<1.25": "11.8%",
      "1.25 - 1.49": "8.51%",
      "1.5 - 1.74": "6.86%",
      "1.75 - 1.99": "2.21%",
      "2 - 2.24": "0.82%",
      "2.25 - 2.4": "0.65%",
      "2.5 - 2.75": "0.42%",
      "2.75 - 2.99": "0.1%",
      ">3": "1.02%"
    }
  },
  "FOCUS": {
    "price": "15.83pln",
    "winChance": 19.999,
    "looseChance": 80.001,
    "profitChances": {
      "<1.25": "7.51%",
      "1.25 - 1.49": "1.92%",
      "1.5 - 1.74": "0.96%",
      "1.75 - 1.99": "0.6%",
      "2 - 2.24": "0.87%",
      "2.25 - 2.4": "0.21%",
      "2.5 - 2.75": "1.7%",
      "2.75 - 2.99": "2.29%",
      ">3": "3.93%"
    }
  },
  "FANG": {
    "price": "146.35pln",
    "winChance": 21.911,
    "looseChance": 78.089,
    "profitChances": {
      "<1.25": "8.92%",
      "1.25 - 1.49": "2.24%",
      "1.5 - 1.74": "5.33%",
      "1.75 - 1.99": "0%",
      "2 - 2.24": "0%",
      "2.25 - 2.4": "1.81%",
      "2.5 - 2.75": "2.4%",
      "2.75 - 2.99": "0%",
      ">3": "1.21%"
    }
  },
  "COBRA": {
    "price": "395.53pln",
    "winChance": 32.046,
    "looseChance": 67.954,
    "profitChances": {
      "<1.25": "7.67%",
      "1.25 - 1.49": "13.92%",
      "1.5 - 1.74": "5.21%",
      "1.75 - 1.99": "0.54%",
      "2 - 2.24": "0.3%",
      "2.25 - 2.4": "0.47%",
      "2.5 - 2.75": "0%",
      "2.75 - 2.99": "0.26%",
      ">3": "3.67%"
    }
  },
  "ROYAL": {
    "price": "59.31pln",
    "winChance": 32.693,
    "looseChance": 67.307,
    "profitChances": {
      "<1.25": "6.83%",
      "1.25 - 1.49": "2.68%",
      "1.5 - 1.74": "4.9%",
      "1.75 - 1.99": "12.59%",
      "2 - 2.24": "1.46%",
      "2.25 - 2.4": "0.68%",
      "2.5 - 2.75": "1.11%",
      "2.75 - 2.99": "1.34%",
      ">3": "1.11%"
    }
  },
  "THUNDER": {
    "price": "79.11pln",
    "winChance": 37.45,
    "looseChance": 62.55,
    "profitChances": {
      "<1.25": "13.56%",
      "1.25 - 1.49": "15.86%",
      "1.5 - 1.74": "4.45%",
      "1.75 - 1.99": "0.68%",
      "2 - 2.24": "1.06%",
      "2.25 - 2.4": "0.5%",
      "2.5 - 2.75": "0%",
      "2.75 - 2.99": "0.09%",
      ">3": "1.24%"
    }
  },
  "TOOTH": {
    "price": "41pln",
    "winChance": 22.445,
    "looseChance": 77.555,
    "profitChances": {
      "<1.25": "1.3%",
      "1.25 - 1.49": "5.39%",
      "1.5 - 1.74": "10.04%",
      "1.75 - 1.99": "2.53%",
      "2 - 2.24": "0.2%",
      "2.25 - 2.4": "0%",
      "2.5 - 2.75": "0%",
      "2.75 - 2.99": "0.5%",
      ">3": "2.48%"
    }
  },
  "BUBBLE": {
    "price": "57.1pln",
    "winChance": 32.674,
    "looseChance": 67.326,
    "profitChances": {
      "<1.25": "16.81%",
      "1.25 - 1.49": "8.16%",
      "1.5 - 1.74": "5.24%",
      "1.75 - 1.99": "0.68%",
      "2 - 2.24": "0.13%",
      "2.25 - 2.4": "0.33%",
      "2.5 - 2.75": "0%",
      "2.75 - 2.99": "0.07%",
      ">3": "1.26%"
    }
  },
  "HIVE": {
    "price": "32.29pln",
    "winChance": 28.426,
    "looseChance": 71.574,
    "profitChances": {
      "<1.25": "7.33%",
      "1.25 - 1.49": "9.04%",
      "1.5 - 1.74": "0%",
      "1.75 - 1.99": "3.17%",
      "2 - 2.24": "6.79%",
      "2.25 - 2.4": "0%",
      "2.5 - 2.75": "0%",
      "2.75 - 2.99": "0.48%",
      ">3": "1.61%"
    }
  },
  "STRIKE": {
    "price": "23.63pln",
    "winChance": 27.158,
    "looseChance": 72.842,
    "profitChances": {
      "<1.25": "3.65%",
      "1.25 - 1.49": "9.49%",
      "1.5 - 1.74": "5.84%",
      "1.75 - 1.99": "6.26%",
      "2 - 2.24": "1.23%",
      "2.25 - 2.4": "0%",
      "2.5 - 2.75": "0%",
      "2.75 - 2.99": "0%",
      ">3": "0.7%"
    }
  },
  "SPLINTER": {
    "price": "68.73pln",
    "winChance": 26.469,
    "looseChance": 73.531,
    "profitChances": {
      "<1.25": "4.36%",
      "1.25 - 1.49": "5.48%",
      "1.5 - 1.74": "5.42%",
      "1.75 - 1.99": "7.03%",
      "2 - 2.24": "0%",
      "2.25 - 2.4": "3.21%",
      "2.5 - 2.75": "0.31%",
      "2.75 - 2.99": "0%",
      ">3": "0.32%"
    }
  },
  "VISION": {
    "price": "123.71pln",
    "winChance": 23.416,
    "looseChance": 76.584,
    "profitChances": {
      "<1.25": "1.92%",
      "1.25 - 1.49": "6.92%",
      "1.5 - 1.74": "7%",
      "1.75 - 1.99": "2.83%",
      "2 - 2.24": "1.18%",
      "2.25 - 2.4": "0%",
      "2.5 - 2.75": "0.2%",
      "2.75 - 2.99": "0%",
      ">3": "3.35%"
    }
  },
  "TOXIC": {
    "price": "6.67pln",
    "winChance": 23.086,
    "looseChance": 76.914,
    "profitChances": {
      "<1.25": "9.38%",
      "1.25 - 1.49": "4.65%",
      "1.5 - 1.74": "2.22%",
      "1.75 - 1.99": "1.43%",
      "2 - 2.24": "3.06%",
      "2.25 - 2.4": "0.24%",
      "2.5 - 2.75": "0%",
      "2.75 - 2.99": "0%",
      ">3": "2.1%"
    }
  },
  "OMEGA": {
    "price": "49.29pln",
    "winChance": 27.736,
    "looseChance": 72.264,
    "profitChances": {
      "<1.25": "2.24%",
      "1.25 - 1.49": "14.83%",
      "1.5 - 1.74": "3.03%",
      "1.75 - 1.99": "4.81%",
      "2 - 2.24": "1.6%",
      "2.25 - 2.4": "0%",
      "2.5 - 2.75": "0.11%",
      "2.75 - 2.99": "0%",
      ">3": "1.11%"
    }
  },
  "DREAM": {
    "price": "97.82pln",
    "winChance": 32.726,
    "looseChance": 67.274,
    "profitChances": {
      "<1.25": "11.56%",
      "1.25 - 1.49": "5.77%",
      "1.5 - 1.74": "13.37%",
      "1.75 - 1.99": "0%",
      "2 - 2.24": "0.36%",
      "2.25 - 2.4": "0%",
      "2.5 - 2.75": "0.29%",
      "2.75 - 2.99": "0.2%",
      ">3": "1.17%"
    }
  },
  "DIABLO": {
    "price": "5.64pln",
    "winChance": 25.836,
    "looseChance": 74.164,
    "profitChances": {
      "<1.25": "0%",
      "1.25 - 1.49": "4.7%",
      "1.5 - 1.74": "18.24%",
      "1.75 - 1.99": "1.17%",
      "2 - 2.24": "0%",
      "2.25 - 2.4": "0%",
      "2.5 - 2.75": "0%",
      "2.75 - 2.99": "0%",
      ">3": "1.74%"
    }
  },
  "SHADOW": {
    "price": "14.16pln",
    "winChance": 28.445,
    "looseChance": 71.555,
    "profitChances": {
      "<1.25": "7.65%",
      "1.25 - 1.49": "7.98%",
      "1.5 - 1.74": "5.65%",
      "1.75 - 1.99": "5.21%",
      "2 - 2.24": "0.64%",
      "2.25 - 2.4": "0%",
      "2.5 - 2.75": "0%",
      "2.75 - 2.99": "0%",
      ">3": "1.32%"
    }
  },
  "ICE BLAST": {
    "price": "1.58pln",
    "winChance": 22.528,
    "looseChance": 77.472,
    "profitChances": {
      "<1.25": "7.55%",
      "1.25 - 1.49": "0%",
      "1.5 - 1.74": "0%",
      "1.75 - 1.99": "0%",
      "2 - 2.24": "3.43%",
      "2.25 - 2.4": "8.51%",
      "2.5 - 2.75": "0%",
      "2.75 - 2.99": "0%",
      ">3": "3.04%"
    }
  },
  "DEADPOOL": {
    "price": "46.68pln",
    "winChance": 33.819,
    "looseChance": 66.181,
    "profitChances": {
      "<1.25": "11.28%",
      "1.25 - 1.49": "7.58%",
      "1.5 - 1.74": "6.64%",
      "1.75 - 1.99": "0%",
      "2 - 2.24": "5.77%",
      "2.25 - 2.4": "2.07%",
      "2.5 - 2.75": "0%",
      "2.75 - 2.99": "0%",
      ">3": "0.47%"
    }
  },
  "ROCKET RACCON": {
    "price": "1.76pln",
    "winChance": 38.968,
    "looseChance": 61.032,
    "profitChances": {
      "<1.25": "15.44%",
      "1.25 - 1.49": "0%",
      "1.5 - 1.74": "5.56%",
      "1.75 - 1.99": "7.51%",
      "2 - 2.24": "1.02%",
      "2.25 - 2.4": "3.49%",
      "2.5 - 2.75": "1.84%",
      "2.75 - 2.99": "0%",
      ">3": "4.1%"
    }
  },
  "BATMAN": {
    "price": "7.53pln",
    "winChance": 27.474,
    "looseChance": 72.526,
    "profitChances": {
      "<1.25": "6.6%",
      "1.25 - 1.49": "12.37%",
      "1.5 - 1.74": "5.54%",
      "1.75 - 1.99": "0%",
      "2 - 2.24": "0%",
      "2.25 - 2.4": "1.25%",
      "2.5 - 2.75": "0.84%",
      "2.75 - 2.99": "0%",
      ">3": "0.87%"
    }
  },
  "VENOM": {
    "price": "92.55pln",
    "winChance": 28.312,
    "looseChance": 71.688,
    "profitChances": {
      "<1.25": "3.87%",
      "1.25 - 1.49": "4.41%",
      "1.5 - 1.74": "10.9%",
      "1.75 - 1.99": "0%",
      "2 - 2.24": "2.9%",
      "2.25 - 2.4": "0%",
      "2.5 - 2.75": "4.44%",
      "2.75 - 2.99": "0%",
      ">3": "1.79%"
    }
  },
  "THANOS": {
    "price": "22.14pln",
    "winChance": 16.412,
    "looseChance": 83.588,
    "profitChances": {
      "<1.25": "6.9%",
      "1.25 - 1.49": "3.19%",
      "1.5 - 1.74": "0.27%",
      "1.75 - 1.99": "1%",
      "2 - 2.24": "0%",
      "2.25 - 2.4": "0%",
      "2.5 - 2.75": "0.3%",
      "2.75 - 2.99": "0%",
      ">3": "4.76%"
    }
  },
  "IRONMAN": {
    "price": "15.02pln",
    "winChance": 31.709,
    "looseChance": 68.291,
    "profitChances": {
      "<1.25": "10.83%",
      "1.25 - 1.49": "2.11%",
      "1.5 - 1.74": "1.37%",
      "1.75 - 1.99": "9.96%",
      "2 - 2.24": "4.83%",
      "2.25 - 2.4": "0%",
      "2.5 - 2.75": "1.29%",
      "2.75 - 2.99": "0.21%",
      ">3": "1.1%"
    }
  },
  "CAPTAIN AMERICA": {
    "price": "34.82pln",
    "winChance": 30.412,
    "looseChance": 69.588,
    "profitChances": {
      "<1.25": "12.43%",
      "1.25 - 1.49": "4.43%",
      "1.5 - 1.74": "7.76%",
      "1.75 - 1.99": "0.88%",
      "2 - 2.24": "0%",
      "2.25 - 2.4": "0.73%",
      "2.5 - 2.75": "0%",
      "2.75 - 2.99": "3.2%",
      ">3": "0.98%"
    }
  },
  "THOR": {
    "price": "9.47pln",
    "winChance": 30.818,
    "looseChance": 69.182,
    "profitChances": {
      "<1.25": "7.75%",
      "1.25 - 1.49": "0%",
      "1.5 - 1.74": "15.87%",
      "1.75 - 1.99": "0%",
      "2 - 2.24": "2.24%",
      "2.25 - 2.4": "0%",
      "2.5 - 2.75": "0.18%",
      "2.75 - 2.99": "0.99%",
      ">3": "2.88%"
    }
  },
  "HULK": {
    "price": "24.13pln",
    "winChance": 41.95,
    "looseChance": 58.05,
    "profitChances": {
      "<1.25": "21.06%",
      "1.25 - 1.49": "10.67%",
      "1.5 - 1.74": "8.21%",
      "1.75 - 1.99": "1.52%",
      "2 - 2.24": "0%",
      "2.25 - 2.4": "0.13%",
      "2.5 - 2.75": "0%",
      "2.75 - 2.99": "0%",
      ">3": "0.36%"
    }
  },
  "VEST": {
    "price": "900.38pln",
    "winChance": 21.786,
    "looseChance": 78.214,
    "profitChances": {
      "<1.25": "4.34%",
      "1.25 - 1.49": "14.65%",
      "1.5 - 1.74": "0.95%",
      "1.75 - 1.99": "0%",
      "2 - 2.24": "0%",
      "2.25 - 2.4": "0%",
      "2.5 - 2.75": "0.3%",
      "2.75 - 2.99": "0.01%",
      ">3": "1.54%"
    }
  },
  "SERPENT": {
    "price": "274.57pln",
    "winChance": 35.28,
    "looseChance": 64.72,
    "profitChances": {
      "<1.25": "18.76%",
      "1.25 - 1.49": "8.93%",
      "1.5 - 1.74": "1.21%",
      "1.75 - 1.99": "2.55%",
      "2 - 2.24": "0%",
      "2.25 - 2.4": "2.04%",
      "2.5 - 2.75": "0%",
      "2.75 - 2.99": "0.06%",
      ">3": "1.74%"
    }
  },
  "ARROW": {
    "price": "592.66pln",
    "winChance": 21.425,
    "looseChance": 78.575,
    "profitChances": {
      "<1.25": "0.36%",
      "1.25 - 1.49": "2.85%",
      "1.5 - 1.74": "0%",
      "1.75 - 1.99": "9.99%",
      "2 - 2.24": "4.96%",
      "2.25 - 2.4": "0%",
      "2.5 - 2.75": "0%",
      "2.75 - 2.99": "0.23%",
      ">3": "3.03%"
    }
  },
  "LORE": {
    "price": "1977.59pln",
    "winChance": 31.947,
    "looseChance": 68.053,
    "profitChances": {
      "<1.25": "22.76%",
      "1.25 - 1.49": "0.4%",
      "1.5 - 1.74": "5.97%",
      "1.75 - 1.99": "1.24%",
      "2 - 2.24": "0.38%",
      "2.25 - 2.4": "0.22%",
      "2.5 - 2.75": "0.08%",
      "2.75 - 2.99": "0.09%",
      ">3": "0.8%"
    }
  },
  "VICE": {
    "price": "1185.5pln",
    "winChance": 24.243,
    "looseChance": 75.757,
    "profitChances": {
      "<1.25": "17%",
      "1.25 - 1.49": "4.62%",
      "1.5 - 1.74": "0.31%",
      "1.75 - 1.99": "0.34%",
      "2 - 2.24": "0.1%",
      "2.25 - 2.4": "0.1%",
      "2.5 - 2.75": "0.57%",
      "2.75 - 2.99": "0.5%",
      ">3": "0.7%"
    }
  },
  "BLOODSHOT": {
    "price": "1582.11pln",
    "winChance": 36.065,
    "looseChance": 63.935,
    "profitChances": {
      "<1.25": "20.08%",
      "1.25 - 1.49": "9.59%",
      "1.5 - 1.74": "2.95%",
      "1.75 - 1.99": "1.32%",
      "2 - 2.24": "1.08%",
      "2.25 - 2.4": "0%",
      "2.5 - 2.75": "0.31%",
      "2.75 - 2.99": "0.05%",
      ">3": "0.69%"
    }
  },
  "TERRORIST": {
    "price": "11.09pln",
    "winChance": 28.967,
    "looseChance": 71.033,
    "profitChances": {
      "<1.25": "5.89%",
      "1.25 - 1.49": "3.66%",
      "1.5 - 1.74": "9.56%",
      "1.75 - 1.99": "4.97%",
      "2 - 2.24": "0.16%",
      "2.25 - 2.4": "0.31%",
      "2.5 - 2.75": "0.08%",
      "2.75 - 2.99": "2.21%",
      ">3": "2.12%"
    }
  },
  "NICE SHOT": {
    "price": "37.57pln",
    "winChance": 33.743,
    "looseChance": 66.257,
    "profitChances": {
      "<1.25": "11.88%",
      "1.25 - 1.49": "3.29%",
      "1.5 - 1.74": "3.84%",
      "1.75 - 1.99": "1.27%",
      "2 - 2.24": "6.57%",
      "2.25 - 2.4": "0%",
      "2.5 - 2.75": "1.41%",
      "2.75 - 2.99": "3.92%",
      ">3": "1.57%"
    }
  },
  "VIPER": {
    "price": "19.75pln",
    "winChance": 25.196,
    "looseChance": 74.804,
    "profitChances": {
      "<1.25": "2.4%",
      "1.25 - 1.49": "6.27%",
      "1.5 - 1.74": "3.52%",
      "1.75 - 1.99": "0%",
      "2 - 2.24": "0%",
      "2.25 - 2.4": "1.31%",
      "2.5 - 2.75": "1.94%",
      "2.75 - 2.99": "2.12%",
      ">3": "7.65%"
    }
  },
  "MASTER": {
    "price": "15.83pln",
    "winChance": 28.444,
    "looseChance": 71.556,
    "profitChances": {
      "<1.25": "0.8%",
      "1.25 - 1.49": "4.94%",
      "1.5 - 1.74": "10.39%",
      "1.75 - 1.99": "5.24%",
      "2 - 2.24": "0%",
      "2.25 - 2.4": "0.36%",
      "2.5 - 2.75": "1.9%",
      "2.75 - 2.99": "3.34%",
      ">3": "0.58%"
    }
  },
  "MARKER": {
    "price": "4.74pln",
    "winChance": 38.132,
    "looseChance": 61.868,
    "profitChances": {
      "<1.25": "5.93%",
      "1.25 - 1.49": "6.2%",
      "1.5 - 1.74": "0%",
      "1.75 - 1.99": "4.88%",
      "2 - 2.24": "18%",
      "2.25 - 2.4": "0%",
      "2.5 - 2.75": "2.47%",
      "2.75 - 2.99": "0%",
      ">3": "0.65%"
    }
  },
  "CRIMSON EMERALD": {
    "price": "49.43pln",
    "winChance": 30.96,
    "looseChance": 69.04,
    "profitChances": {
      "<1.25": "16.04%",
      "1.25 - 1.49": "8.31%",
      "1.5 - 1.74": "0%",
      "1.75 - 1.99": "0%",
      "2 - 2.24": "4.68%",
      "2.25 - 2.4": "0%",
      "2.5 - 2.75": "0%",
      "2.75 - 2.99": "0%",
      ">3": "1.93%"
    }
  },
  "THE EXPENDABLES": {
    "price": "63.86pln",
    "winChance": 28.431,
    "looseChance": 71.569,
    "profitChances": {
      "<1.25": "1.38%",
      "1.25 - 1.49": "0%",
      "1.5 - 1.74": "13.31%",
      "1.75 - 1.99": "9.1%",
      "2 - 2.24": "0%",
      "2.25 - 2.4": "0.74%",
      "2.5 - 2.75": "1.07%",
      "2.75 - 2.99": "0%",
      ">3": "2.41%"
    }
  },
  "DRAGON": {
    "price": "19.44pln",
    "winChance": 31.598,
    "looseChance": 68.402,
    "profitChances": {
      "<1.25": "7.79%",
      "1.25 - 1.49": "9.59%",
      "1.5 - 1.74": "5.7%",
      "1.75 - 1.99": "1.8%",
      "2 - 2.24": "0.34%",
      "2.25 - 2.4": "0%",
      "2.5 - 2.75": "0%",
      "2.75 - 2.99": "0%",
      ">3": "6.38%"
    }
  },
  "PIKA PIKA": {
    "price": "18.27pln",
    "winChance": 17.103,
    "looseChance": 82.897,
    "profitChances": {
      "<1.25": "4.41%",
      "1.25 - 1.49": "0%",
      "1.5 - 1.74": "2.05%",
      "1.75 - 1.99": "1.97%",
      "2 - 2.24": "1.3%",
      "2.25 - 2.4": "0.22%",
      "2.5 - 2.75": "5.44%",
      "2.75 - 2.99": "0.21%",
      ">3": "1.51%"
    }
  },
  "AVALANCHE": {
    "price": "3.7pln",
    "winChance": 24.418,
    "looseChance": 75.582,
    "profitChances": {
      "<1.25": "11.15%",
      "1.25 - 1.49": "0.18%",
      "1.5 - 1.74": "0.1%",
      "1.75 - 1.99": "8.59%",
      "2 - 2.24": "0%",
      "2.25 - 2.4": "1.14%",
      "2.5 - 2.75": "1%",
      "2.75 - 2.99": "0.34%",
      ">3": "1.92%"
    }
  },
  "SPIDER": {
    "price": "31.66pln",
    "winChance": 21.255,
    "looseChance": 78.745,
    "profitChances": {
      "<1.25": "2.26%",
      "1.25 - 1.49": "2.14%",
      "1.5 - 1.74": "0%",
      "1.75 - 1.99": "6.15%",
      "2 - 2.24": "1.55%",
      "2.25 - 2.4": "6.14%",
      "2.5 - 2.75": "0%",
      "2.75 - 2.99": "0.15%",
      ">3": "2.87%"
    }
  },
  "TEETH": {
    "price": "2.8pln",
    "winChance": 19.782,
    "looseChance": 80.218,
    "profitChances": {
      "<1.25": "1.04%",
      "1.25 - 1.49": "8.44%",
      "1.5 - 1.74": "1.91%",
      "1.75 - 1.99": "0.62%",
      "2 - 2.24": "0.84%",
      "2.25 - 2.4": "3.01%",
      "2.5 - 2.75": "1.59%",
      "2.75 - 2.99": "0.51%",
      ">3": "1.82%"
    }
  },
  "MAFIA": {
    "price": "15.02pln",
    "winChance": 25.297,
    "looseChance": 74.703,
    "profitChances": {
      "<1.25": "10.47%",
      "1.25 - 1.49": "3.33%",
      "1.5 - 1.74": "1.58%",
      "1.75 - 1.99": "1.21%",
      "2 - 2.24": "7.61%",
      "2.25 - 2.4": "0%",
      "2.5 - 2.75": "0%",
      "2.75 - 2.99": "0.86%",
      ">3": "0.24%"
    }
  },
  "GRADIENT": {
    "price": "15.51pln",
    "winChance": 32.053,
    "looseChance": 67.947,
    "profitChances": {
      "<1.25": "0%",
      "1.25 - 1.49": "7.58%",
      "1.5 - 1.74": "11.25%",
      "1.75 - 1.99": "3.09%",
      "2 - 2.24": "5.37%",
      "2.25 - 2.4": "2.41%",
      "2.5 - 2.75": "0%",
      "2.75 - 2.99": "0%",
      ">3": "2.34%"
    }
  },
  "BEAST": {
    "price": "2.57pln",
    "winChance": 26.895,
    "looseChance": 73.105,
    "profitChances": {
      "<1.25": "1.14%",
      "1.25 - 1.49": "9.55%",
      "1.5 - 1.74": "0.64%",
      "1.75 - 1.99": "0%",
      "2 - 2.24": "3.56%",
      "2.25 - 2.4": "7.2%",
      "2.5 - 2.75": "3.54%",
      "2.75 - 2.99": "0.07%",
      ">3": "1.2%"
    }
  },
  "BUMBLEBEE": {
    "price": "111.94pln",
    "winChance": 24.845,
    "looseChance": 75.155,
    "profitChances": {
      "<1.25": "7.13%",
      "1.25 - 1.49": "7.83%",
      "1.5 - 1.74": "1.91%",
      "1.75 - 1.99": "2.54%",
      "2 - 2.24": "3.97%",
      "2.25 - 2.4": "0%",
      "2.5 - 2.75": "0.39%",
      "2.75 - 2.99": "0.12%",
      ">3": "0.97%"
    }
  },
  "LAZURE": {
    "price": "7.53pln",
    "winChance": 31.047,
    "looseChance": 68.953,
    "profitChances": {
      "<1.25": "8.21%",
      "1.25 - 1.49": "7.6%",
      "1.5 - 1.74": "6.95%",
      "1.75 - 1.99": "0.56%",
      "2 - 2.24": "3.58%",
      "2.25 - 2.4": "0%",
      "2.5 - 2.75": "0.64%",
      "2.75 - 2.99": "0.97%",
      ">3": "2.54%"
    }
  },
  "JOKER": {
    "price": "197.76pln",
    "winChance": 31.419,
    "looseChance": 68.581,
    "profitChances": {
      "<1.25": "15.35%",
      "1.25 - 1.49": "1.41%",
      "1.5 - 1.74": "3.31%",
      "1.75 - 1.99": "6.13%",
      "2 - 2.24": "0%",
      "2.25 - 2.4": "0%",
      "2.5 - 2.75": "0%",
      "2.75 - 2.99": "0%",
      ">3": "5.21%"
    }
  },
  "BULLET": {
    "price": "5.64pln",
    "winChance": 35.035,
    "looseChance": 64.965,
    "profitChances": {
      "<1.25": "24.3%",
      "1.25 - 1.49": "1.53%",
      "1.5 - 1.74": "4.13%",
      "1.75 - 1.99": "0%",
      "2 - 2.24": "4.17%",
      "2.25 - 2.4": "0.48%",
      "2.5 - 2.75": "0%",
      "2.75 - 2.99": "0%",
      ">3": "0.41%"
    }
  },
  "BANANA": {
    "price": "5.37pln",
    "winChance": 26.623,
    "looseChance": 73.377,
    "profitChances": {
      "<1.25": "6.99%",
      "1.25 - 1.49": "0.36%",
      "1.5 - 1.74": "3.54%",
      "1.75 - 1.99": "10.48%",
      "2 - 2.24": "0%",
      "2.25 - 2.4": "4.26%",
      "2.5 - 2.75": "0%",
      "2.75 - 2.99": "0%",
      ">3": "0.99%"
    }
  },
  "RAZOR": {
    "price": "43.52pln",
    "winChance": 29.986,
    "looseChance": 70.014,
    "profitChances": {
      "<1.25": "3.25%",
      "1.25 - 1.49": "16.92%",
      "1.5 - 1.74": "5%",
      "1.75 - 1.99": "0%",
      "2 - 2.24": "0%",
      "2.25 - 2.4": "2.36%",
      "2.5 - 2.75": "0%",
      "2.75 - 2.99": "0%",
      ">3": "2.46%"
    }
  },
  "AK-47": {
    "price": "19.75pln",
    "winChance": 25.185,
    "looseChance": 74.815,
    "profitChances": {
      "<1.25": "7.39%",
      "1.25 - 1.49": "1.42%",
      "1.5 - 1.74": "3.86%",
      "1.75 - 1.99": "2.2%",
      "2 - 2.24": "0.66%",
      "2.25 - 2.4": "0.63%",
      "2.5 - 2.75": "0%",
      "2.75 - 2.99": "0.1%",
      ">3": "2.2%"
    }
  },
  "AWP": {
    "price": "17.41pln",
    "winChance": 13.092,
    "looseChance": 86.908,
    "profitChances": {
      "<1.25": "0%",
      "1.25 - 1.49": "0%",
      "1.5 - 1.74": "0%",
      "1.75 - 1.99": "5.77%",
      "2 - 2.24": "0%",
      "2.25 - 2.4": "3.74%",
      "2.5 - 2.75": "1.04%",
      "2.75 - 2.99": "0.03%",
      ">3": "2.51%"
    }
  },
  "KNIVES": {
    "price": "375.73pln",
    "winChance": 8.834,
    "looseChance": 91.166,
    "profitChances": {
      "<1.25": "7.42%",
      "1.25 - 1.49": "0.22%",
      "1.5 - 1.74": "0.22%",
      "1.75 - 1.99": "0.19%",
      "2 - 2.24": "0.1%",
      "2.25 - 2.4": "0%",
      "2.5 - 2.75": "0.03%",
      "2.75 - 2.99": "0.02%",
      ">3": "0.63%"
    }
  },
  "GLOVES": {
    "price": "636.81pln",
    "winChance": 26.457,
    "looseChance": 73.543,
    "profitChances": {
      "<1.25": "8.13%",
      "1.25 - 1.49": "8.82%",
      "1.5 - 1.74": "2.05%",
      "1.75 - 1.99": "3.34%",
      "2 - 2.24": "1.63%",
      "2.25 - 2.4": "1.02%",
      "2.5 - 2.75": "0%",
      "2.75 - 2.99": "0.1%",
      ">3": "1.37%"
    }
  },
  "AGENT": {
    "price": "5.32pln",
    "winChance": 13.598,
    "looseChance": 86.402,
    "profitChances": {
      "<1.25": "4.06%",
      "1.25 - 1.49": "5.25%",
      "1.5 - 1.74": "0.3%",
      "1.75 - 1.99": "0.31%",
      "2 - 2.24": "0.25%",
      "2.25 - 2.4": "2.65%",
      "2.5 - 2.75": "0%",
      "2.75 - 2.99": "0.17%",
      ">3": "0.63%"
    }
  },
  "GLOCK-18": {
    "price": "5.55pln",
    "winChance": 15.222,
    "looseChance": 84.778,
    "profitChances": {
      "<1.25": "3.98%",
      "1.25 - 1.49": "2.05%",
      "1.5 - 1.74": "2.68%",
      "1.75 - 1.99": "0.32%",
      "2 - 2.24": "0%",
      "2.25 - 2.4": "0%",
      "2.5 - 2.75": "0.23%",
      "2.75 - 2.99": "1.44%",
      ">3": "4.52%"
    }
  },
  "M4": {
    "price": "19.12pln",
    "winChance": 32.194,
    "looseChance": 67.806,
    "profitChances": {
      "<1.25": "8.6%",
      "1.25 - 1.49": "10.17%",
      "1.5 - 1.74": "4.67%",
      "1.75 - 1.99": "1.1%",
      "2 - 2.24": "3.6%",
      "2.25 - 2.4": "1.18%",
      "2.5 - 2.75": "0.5%",
      "2.75 - 2.99": "0.18%",
      ">3": "2.19%"
    }
  },
  "USP-S": {
    "price": "5.95pln",
    "winChance": 23.832,
    "looseChance": 76.168,
    "profitChances": {
      "<1.25": "8.54%",
      "1.25 - 1.49": "3.16%",
      "1.5 - 1.74": "5.06%",
      "1.75 - 1.99": "2.34%",
      "2 - 2.24": "0%",
      "2.25 - 2.4": "0%",
      "2.5 - 2.75": "0%",
      "2.75 - 2.99": "2.64%",
      ">3": "2.09%"
    }
  },
  "NEW KNIVES": {
    "price": "474.63pln",
    "winChance": 15.636,
    "looseChance": 84.364,
    "profitChances": {
      "<1.25": "9.84%",
      "1.25 - 1.49": "3.09%",
      "1.5 - 1.74": "0.15%",
      "1.75 - 1.99": "0.46%",
      "2 - 2.24": "0.36%",
      "2.25 - 2.4": "0.46%",
      "2.5 - 2.75": "0.14%",
      "2.75 - 2.99": "0.22%",
      ">3": "0.92%"
    }
  },
  "MILSPEC": {
    "price": "1.17pln",
    "winChance": 22.435,
    "looseChance": 77.565,
    "profitChances": {
      "<1.25": "1.72%",
      "1.25 - 1.49": "5.26%",
      "1.5 - 1.74": "3.27%",
      "1.75 - 1.99": "0.19%",
      "2 - 2.24": "3.73%",
      "2.25 - 2.4": "0.2%",
      "2.5 - 2.75": "0.33%",
      "2.75 - 2.99": "1.16%",
      ">3": "2.41%"
    }
  },
  "RESTRICTED": {
    "price": "7.53pln",
    "winChance": 19.879,
    "looseChance": 80.121,
    "profitChances": {
      "<1.25": "6.77%",
      "1.25 - 1.49": "5.5%",
      "1.5 - 1.74": "2.93%",
      "1.75 - 1.99": "1.29%",
      "2 - 2.24": "0.75%",
      "2.25 - 2.4": "1.36%",
      "2.5 - 2.75": "0%",
      "2.75 - 2.99": "0.04%",
      ">3": "1.26%"
    }
  },
  "COVERT": {
    "price": "27.29pln",
    "winChance": 38.91,
    "looseChance": 61.09,
    "profitChances": {
      "<1.25": "25.5%",
      "1.25 - 1.49": "6.63%",
      "1.5 - 1.74": "4.87%",
      "1.75 - 1.99": "0%",
      "2 - 2.24": "0.61%",
      "2.25 - 2.4": "0.17%",
      "2.5 - 2.75": "0.66%",
      "2.75 - 2.99": "0%",
      ">3": "0.47%"
    }
  },
  "GOLD DIGGER": {
    "price": 480,
    "pricePerPln": "346.04"
  },
  "FOSTER": {
    "price": 610,
    "pricePerPln": "319.10"
  },
  "SHARK": {
    "price": 680,
    "pricePerPln": "319.83"
  },
  "RUBIN RAIN": {
    "price": 840,
    "pricePerPln": "360.75"
  },
  "PREDATOR": {
    "price": 1200,
    "pricePerPln": "281.32"
  },
  "RUBY": {
    "price": 1300,
    "pricePerPln": "338.48"
  },
  "AMETHYST LIGHT": {
    "price": 1400,
    "pricePerPln": "353.75"
  },
  "OPTIMAL": {
    "price": 1930,
    "pricePerPln": "346.83"
  },
  "ATUM": {
    "price": 2670,
    "pricePerPln": "350.40"
  },
  "WRAP": {
    "price": 4900,
    "pricePerPln": "393.23"
  },
  "SOLAR": {
    "price": 5600,
    "pricePerPln": "389.89"
  },
  "DIAMOND SKY": {
    "price": 6200,
    "pricePerPln": "361.37"
  },
  "SAMURAI": {
    "price": 9900,
    "pricePerPln": "348.41"
  },
  "WIND": {
    "price": 12500,
    "pricePerPln": "384.82"
  },
  "EMERALD CUT": {
    "price": 19200,
    "pricePerPln": "393.79"
  }
}